duet/__init__.py
duet/_version.py
duet/aitertools.py
duet/api.py
duet/api_test.py
duet/futuretools.py
duet/futuretools_test.py
duet/impl.py
duet/impl_test.py
duet/py.typed
duet/test.py
duet/typing.py
duet-0.2.9.dist-info/LICENSE
duet-0.2.9.dist-info/METADATA
duet-0.2.9.dist-info/WHEEL
duet-0.2.9.dist-info/top_level.txt
duet-0.2.9.dist-info/RECORD
