Metadata-Version: 2.1
Name: duet
Version: 0.2.9
Summary: A simple future-based async library for python.
Home-page: http://github.com/google/duet
Author: The Duet Authors
Author-email: maffoo@google.com
License: Apache 2
Platform: UNKNOWN
Requires-Python: >=3.9.0
Provides-Extra: dev_env
License-File: LICENSE
